libbiosmoothercpp.cpython-39-x86_64-linux-gnu.so
libbiosmoother/compare_tsv.py
libbiosmoother/_import_lib_bio_smoother_cpp.py
libbiosmoother/test.py
libbiosmoother/export.py
libbiosmoother/cooler_interface.py
libbiosmoother/parameters.py
libbiosmoother/cli.py
libbiosmoother/higlass.py
libbiosmoother/indexer.py
libbiosmoother/quarry.py
libbiosmoother/benchmark_runtime.py
libbiosmoother/_parse_and_group_reads.py
libbiosmoother/__init__.py
libbiosmoother/conf/button_names.json
libbiosmoother/conf/default.json
libbiosmoother/conf/valid.json
libbiosmoother/conf/descriptions.json
libbiosmoother/conf/button_tabs.json
libbiosmoother-1.6.4.dist-info/RECORD
libbiosmoother-1.6.4.dist-info/LICENSE
libbiosmoother-1.6.4.dist-info/METADATA
libbiosmoother-1.6.4.dist-info/entry_points.txt
libbiosmoother-1.6.4.dist-info/top_level.txt
libbiosmoother-1.6.4.dist-info/WHEEL
libbiosmoother-1.6.4.data/data/libbiosmoother/button_names.json
libbiosmoother-1.6.4.data/data/libbiosmoother/default.json
libbiosmoother-1.6.4.data/data/libbiosmoother/valid.json
libbiosmoother-1.6.4.data/data/libbiosmoother/descriptions.json
libbiosmoother-1.6.4.data/data/libbiosmoother/button_tabs.json
libbiosmoother.libs/libgomp-a34b3233.so.1.0.0
