Metadata-Version: 2.1
Name: libbiosmoother
Version: 1.6.4
Summary: On-the-fly processing of interactome data
Home-page: https://github.com/Siegel-Lab/libBioSmoother
Author: Markus Schmidt
License: MIT
Classifier: Development Status :: 3 - Alpha
Classifier: Intended Audience :: Science/Research
Classifier: Operating System :: MacOS :: MacOS X
Classifier: Operating System :: Microsoft :: Windows
Classifier: Operating System :: POSIX :: Linux
Classifier: Programming Language :: Python :: 3
Classifier: Programming Language :: Python :: 3.9
Requires-Python: >=3.8
License-File: LICENSE
Requires-Dist: scipy
Requires-Dist: statsmodels
Requires-Dist: scikit-learn
Provides-Extra: test
Requires-Dist: pytest ; extra == 'test'
